wise_mise_mcp/__init__.py
wise_mise_mcp/__main__.py
wise_mise_mcp/additional_experts.py
wise_mise_mcp/analyzer.py
wise_mise_mcp/experts.py
wise_mise_mcp/manager.py
wise_mise_mcp/models.py
wise_mise_mcp/server.py
wise_mise_mcp-0.1.1.dist-info/METADATA
wise_mise_mcp-0.1.1.dist-info/WHEEL
wise_mise_mcp-0.1.1.dist-info/entry_points.txt
wise_mise_mcp-0.1.1.dist-info/licenses/LICENSE
wise_mise_mcp-0.1.1.dist-info/RECORD
