Metadata-Version: 2.4
Name: wise-mise-mcp
Version: 0.1.1
Summary: An intelligent MCP server for wise mise task management and organization
Project-URL: Homepage, https://github.com/delorenj/wise-mise-mcp
Project-URL: Repository, https://github.com/delorenj/wise-mise-mcp.git
Project-URL: Issues, https://github.com/delorenj/wise-mise-mcp/issues
Project-URL: Discussions, https://github.com/delorenj/wise-mise-mcp/discussions
Project-URL: Changelog, https://github.com/delorenj/wise-mise-mcp/blob/main/docs/CHANGELOG.md
Project-URL: Documentation, https://github.com/delorenj/wise-mise-mcp#readme
Author-email: Jarad DeLorenzo <jaradd@gmail.com>
License: MIT
License-File: LICENSE
Keywords: ai-assistant,automation,build-tools,development,intelligent,mcp,mise,mise-en-place,task-management,workflow
Classifier: Development Status :: 4 - Beta
Classifier: Environment :: Console
Classifier: Intended Audience :: Developers
Classifier: License :: OSI Approved :: MIT License
Classifier: Operating System :: OS Independent
Classifier: Programming Language :: Python :: 3
Classifier: Programming Language :: Python :: 3.11
Classifier: Programming Language :: Python :: 3.12
Classifier: Programming Language :: Python :: 3.13
Classifier: Topic :: Software Development :: Build Tools
Classifier: Topic :: Software Development :: Libraries :: Python Modules
Classifier: Topic :: System :: Systems Administration
Classifier: Topic :: Utilities
Classifier: Typing :: Typed
Requires-Python: >=3.11
Requires-Dist: fastmcp>=2.11.3
Requires-Dist: networkx>=3.5
Requires-Dist: pydantic>=2.11.7
Requires-Dist: tomli-w>=1.2.0
Requires-Dist: tomli>=2.2.1; python_version < '3.11'
Provides-Extra: build
Requires-Dist: build>=1.0.0; extra == 'build'
Requires-Dist: twine>=4.0.0; extra == 'build'
Provides-Extra: dev
Requires-Dist: black>=23.0.0; extra == 'dev'
Requires-Dist: mypy>=1.5.0; extra == 'dev'
Requires-Dist: pytest-asyncio>=0.21.0; extra == 'dev'
Requires-Dist: pytest-cov>=4.0.0; extra == 'dev'
Requires-Dist: pytest>=8.0.0; extra == 'dev'
Requires-Dist: ruff>=0.1.0; extra == 'dev'
Requires-Dist: types-toml; extra == 'dev'
Provides-Extra: docs
Requires-Dist: myst-parser>=2.0.0; extra == 'docs'
Requires-Dist: sphinx-rtd-theme>=1.3.0; extra == 'docs'
Requires-Dist: sphinx>=7.0.0; extra == 'docs'
